odoo10_addon_hr_holidays_validity_date-10.0.1.0.0.99.dev8-py2.7-nspkg.pth
odoo/addons/hr_holidays_validity_date/README.rst
odoo/addons/hr_holidays_validity_date/__init__.py
odoo/addons/hr_holidays_validity_date/__manifest__.py
odoo/addons/hr_holidays_validity_date/i18n/ar.po
odoo/addons/hr_holidays_validity_date/i18n/cs_CZ.po
odoo/addons/hr_holidays_validity_date/i18n/de.po
odoo/addons/hr_holidays_validity_date/i18n/es.po
odoo/addons/hr_holidays_validity_date/i18n/fr.po
odoo/addons/hr_holidays_validity_date/i18n/hr.po
odoo/addons/hr_holidays_validity_date/i18n/hr_HR.po
odoo/addons/hr_holidays_validity_date/i18n/hr_holidays_validity_date.pot
odoo/addons/hr_holidays_validity_date/i18n/sl.po
odoo/addons/hr_holidays_validity_date/models/__init__.py
odoo/addons/hr_holidays_validity_date/models/hr_holidays.py
odoo/addons/hr_holidays_validity_date/static/description/icon.png
odoo/addons/hr_holidays_validity_date/tests/__init__.py
odoo/addons/hr_holidays_validity_date/tests/test_hr_holidays_validity_date.py
odoo/addons/hr_holidays_validity_date/views/hr_holidays_view.xml
odoo10_addon_hr_holidays_validity_date-10.0.1.0.0.99.dev8.dist-info/METADATA
odoo10_addon_hr_holidays_validity_date-10.0.1.0.0.99.dev8.dist-info/RECORD
odoo10_addon_hr_holidays_validity_date-10.0.1.0.0.99.dev8.dist-info/WHEEL
odoo10_addon_hr_holidays_validity_date-10.0.1.0.0.99.dev8.dist-info/namespace_packages.txt
odoo10_addon_hr_holidays_validity_date-10.0.1.0.0.99.dev8.dist-info/top_level.txt
